{
  "root": "/home/tom/Bureau/Developpement/Git/MOwnR/",
  "vrwind": "https://static.virtualregatta.com/winds/",
  "storage": {
    "src": "Src/",
    "data": {
      "wnd": "Data/Wnd/",
      "grib": "Data/Gribs/",
      "polar": "Data/Polaires/",
      "map": "Data/MapsVR/",
      "iso": "Data/Isochrones/",
      "folium": "Data/Folium/"
    }
  },
  "api": {
    "url": "https://roboats.virtualregatta.com/api/",
    "leg": "infos/slow",
    "bs": "infos/fast",
    "ba": "boat/actions",
    "raceId": 531,
    "leg_num": 1,
    "login": {
      "subUrl": "login",
      "headers": {
        "accept": "*/*",
        "Content-Type": "application/json"
      }
    },
    "slow": {
      "subUrl": "infos/slow"
    },
    "fast": {
      "subUrl": "infos/fast"
    }
  }
}